causal_sklearn/__init__.py
causal_sklearn/_version.py
causal_sklearn/classifier.py
causal_sklearn/data_processing.py
causal_sklearn/regressor.py
causal_sklearn/utils.py
causal_sklearn/_causal_engine/__init__.py
causal_sklearn/_causal_engine/engine.py
causal_sklearn/_causal_engine/heads.py
causal_sklearn/_causal_engine/math_utils.py
causal_sklearn/_causal_engine/networks.py
causal_sklearn-0.1.0.dist-info/LICENSE
causal_sklearn-0.1.0.dist-info/METADATA
causal_sklearn-0.1.0.dist-info/WHEEL
causal_sklearn-0.1.0.dist-info/top_level.txt
causal_sklearn-0.1.0.dist-info/RECORD
