Metadata-Version: 2.1
Name: causal-sklearn
Version: 0.1.0
Summary: Scikit-learn compatible implementation of CausalEngine for causal machine learning
Home-page: https://github.com/1587causalai/causal-sklearn
Author: CausalEngine Team
Author-email: 
Maintainer: CausalEngine Team
License: Apache-2.0
Project-URL: Homepage, https://github.com/1587causalai/causal-sklearn
Project-URL: Bug Reports, https://github.com/1587causalai/causal-sklearn/issues
Project-URL: Source, https://github.com/1587causalai/causal-sklearn
Project-URL: Documentation, https://github.com/1587causalai/causal-sklearn/tree/main/docs
Keywords: causal-inference,machine-learning,scikit-learn,neural-networks,regression,classification,causality
Classifier: Development Status :: 3 - Alpha
Classifier: Intended Audience :: Developers
Classifier: Intended Audience :: Science/Research
Classifier: License :: OSI Approved :: Apache Software License
Classifier: Operating System :: OS Independent
Classifier: Programming Language :: Python :: 3
Classifier: Programming Language :: Python :: 3.8
Classifier: Programming Language :: Python :: 3.9
Classifier: Programming Language :: Python :: 3.10
Classifier: Programming Language :: Python :: 3.11
Classifier: Topic :: Scientific/Engineering :: Artificial Intelligence
Classifier: Topic :: Software Development :: Libraries :: Python Modules
Requires-Python: >=3.8
License-File: LICENSE
Requires-Dist: numpy >=1.21.0
Requires-Dist: scipy >=1.7.0
Requires-Dist: scikit-learn >=1.0.0
Requires-Dist: torch >=1.10.0
Requires-Dist: pandas >=1.3.0
Provides-Extra: dev
Requires-Dist: pytest >=6.0 ; extra == 'dev'
Requires-Dist: pytest-cov >=2.0 ; extra == 'dev'
Requires-Dist: black >=21.0 ; extra == 'dev'
Requires-Dist: flake8 >=3.8 ; extra == 'dev'
Requires-Dist: mypy >=0.800 ; extra == 'dev'
Provides-Extra: docs
Requires-Dist: sphinx >=4.0 ; extra == 'docs'
Requires-Dist: sphinx-rtd-theme >=1.0 ; extra == 'docs'
Provides-Extra: examples
Requires-Dist: matplotlib >=3.5.0 ; extra == 'examples'
Requires-Dist: seaborn >=0.11.0 ; extra == 'examples'
